{
    "0b9976c4bf5f5dfc9948de0c66cfa7f26d1f8416": {
        "en": "Lithuanian Sports University",
        "lt": "Lietuvos sporto universitetas"
    },
    "0cb442e5689acc1b2b575d6c49cbfd3ce56ee0fa": {
        "en": "Vilnius University of Applied Sciences",
        "lt": "Vilniaus kolegija"
    },
    "0feea5caed07e3693e9d57e54f3be21ff723257d": {
        "en": "Lithuanian Academy of Music and Theatre",
        "lt": "Lietuvos muzikos ir teatro akademija"
    },
    "12905f5c791e44ab5495474f82d20fd6a5d2b6c6": {
        "en": "Alytus University of Applied Sciences",
        "lt": "Alytaus kolegija"
    },
    "1ed59d4dd978c5043174b7079d7e04bcc67b2b74": {
        "en": "Kaunas University of Technology",
        "lt": "Kauno technologijos universitetas"
    },
    "2630dee81d4c017fc0da435f37d85f97dd4e9efc": {
        "en": "Mykolas Romeris University",
        "lt": "Mykolo Romerio universitetas"
    },
    "4199ccc62c0a3310d4405b8a91d5cca4c8ab7f0a": {
        "en": "Vilnius Gediminas Technical University",
        "lt": "Vilniaus Gedimino technikos universitetas"
    },
    "599781a9d67ec6b6ec4339aff8219e518eedfc5a": {
        "en": "Klaipeda State University of Applied Sciences",
        "lt": "Klaip\u0117dos valstybin\u0117 kolegija"
    },
    "6448fe939134e7f770882203a619d1c4dfa2b998": {
        "en": "General Jonas \u017demaitis Military Academy of Lithuania",
        "lt": "Generolo Jono \u017demai\u010dio Lietuvos karo akademija"
    },
    "82630d4ceb122e965f07e98a721fac157ed4a6ba": {
        "en": "Institute of the Lithuanian Language",
        "lt": "Lietuvi\u0173 kalbos institutas"
    },
    "89c0d7983368fc92fc79d0943d1714783c2840b0": {
        "en": "ISM University of Management and Economics",
        "lt": "ISM Vadybos ir ekonomikos universitetas"
    },
    "8ea022ef906448ef7a301230b2a637b4c50c02f4": {
        "en": "Vytautas Magnus University",
        "lt": "Vytauto Did\u017eiojo universitetas"
    },
    "8f5f8f54836d68864753fc0446c8cf29277b7cd9": {
        "en": "European Humanities University",
        "lt": "Europos humanitarinis universitetas"
    },
    "96cc299eb5936089db8a71ff5bb0b60afc589143": {
        "en": "Kaunas University of Applied Sciences",
        "lt": "Kauno kolegija"
    },
    "c39dce1ad11bbe64aa3c1b6e9e470ae4b6d1d185": {
        "en": "Lithuanian Research Centre for Agriculture and Forestry",
        "lt": "Lietuvos agrarini\u0173 ir mi\u0161k\u0173 moksl\u0173 centras"
    },
    "d27e0905e5ddda20720b2c2717dc8fb39f47f639": {
        "en": "Marijampole College",
        "lt": "Marijampol\u0117s kolegija"
    },
    "d810df7c82f34eb79ae7d1a6fcd1ae8d4f10659a": {
        "en": "Lithuanian University of Health Sciences",
        "lt": "Lietuvos sveikatos moksl\u0173 universitetas"
    },
    "de0c6556025a39b2972a722a591a644a29dd8cba": {
        "en": "Vilnius University",
        "lt": "Vilniaus universitetas"
    },
    "e12cffeb5059ff38900c99affd0980bf11bb21df": {
        "en": "Klaipeda University",
        "lt": "Klaip\u0117dos universitetas"
    },
    "fdb89425e763d3a4d0b471222b83a5a797b55153": {
        "en": "Utena University of Applied Sciences",
        "lt": "Utenos kolegija"
    }
}